swarmauri_base/agents/AgentBase.py
swarmauri_base/agents/AgentConversationMixin.py
swarmauri_base/agents/AgentRetrieveMixin.py
swarmauri_base/agents/AgentSystemContextMixin.py
swarmauri_base/agents/AgentToolMixin.py
swarmauri_base/agents/AgentVectorStoreMixin.py
swarmauri_base/agents/__init__.py
swarmauri_base/chains/ChainBase.py
swarmauri_base/chains/ChainContextBase.py
swarmauri_base/chains/ChainStepBase.py
swarmauri_base/chains/PromptContextChainBase.py
swarmauri_base/chains/__init__.py
swarmauri_base/chunkers/ChunkerBase.py
swarmauri_base/chunkers/__init__.py
swarmauri_base/control_panels/ControlPanelBase.py
swarmauri_base/control_panels/__init__.py
swarmauri_base/conversations/ConversationBase.py
swarmauri_base/conversations/ConversationSystemContextMixin.py
swarmauri_base/conversations/__init__.py
swarmauri_base/dataconnectors/DataConnectorBase.py
swarmauri_base/dataconnectors/__init__.py
swarmauri_base/distances/DistanceBase.py
swarmauri_base/distances/VisionDistanceBase.py
swarmauri_base/distances/__init__.py
swarmauri_base/document_stores/DocumentStoreBase.py
swarmauri_base/document_stores/DocumentStoreRetrieveBase.py
swarmauri_base/document_stores/__init__.py
swarmauri_base/documents/DocumentBase.py
swarmauri_base/documents/__init__.py
swarmauri_base/embeddings/EmbeddingBase.py
swarmauri_base/embeddings/VisionEmbeddingBase.py
swarmauri_base/embeddings/__init__.py
swarmauri_base/factories/FactoryBase.py
swarmauri_base/factories/_init__.py
swarmauri_base/image_gens/ImageGenBase.py
swarmauri_base/image_gens/__init__.py
swarmauri_base/llms/LLMBase.py
swarmauri_base/llms/__init__.py
swarmauri_base/measurements/MeasurementAggregateMixin.py
swarmauri_base/measurements/MeasurementBase.py
swarmauri_base/measurements/MeasurementCalculateMixin.py
swarmauri_base/measurements/MeasurementThresholdMixin.py
swarmauri_base/measurements/__init__.py
swarmauri_base/messages/MessageBase.py
swarmauri_base/messages/__init__.py
swarmauri_base/ocrs/OCRBase.py
swarmauri_monorepo-0.6.2.dev3.dist-info/METADATA
swarmauri_monorepo-0.6.2.dev3.dist-info/WHEEL
swarmauri_monorepo-0.6.2.dev3.dist-info/licenses/LICENSE
swarmauri_monorepo-0.6.2.dev3.dist-info/RECORD
