Metadata-Version: 2.4
Name: swarmauri-monorepo
Version: 0.6.2.dev3
Summary: Monorepo for multiple interdependent Swarmauri Python packages
Author-email: Jacob Stewart <jacob@swarmauri.com>
License:                                  Apache License
License-File: LICENSE
Requires-Python: <3.13,>=3.10
